atscale/__init__.py
atscale/base/__init__.py
atscale/base/config.py
atscale/base/endpoints.py
atscale/base/enums.py
atscale/base/secrets_manager.py
atscale/base/templates.py
atscale/client/__init__.py
atscale/client/client.py
atscale/connection/__init__.py
atscale/connection/connection.py
atscale/data_model/__init__.py
atscale/data_model/data_model.py
atscale/data_model/data_model_helpers.py
atscale/db/__init__.py
atscale/db/connections/__init__.py
atscale/db/connections/bigquery.py
atscale/db/connections/databricks.py
atscale/db/connections/iris.py
atscale/db/connections/mssql.py
atscale/db/connections/postgres.py
atscale/db/connections/redshift.py
atscale/db/connections/snowflake.py
atscale/db/connections/synapse.py
atscale/db/sql_connection.py
atscale/db/sqlalchemy_connection.py
atscale/eda/__init__.py
atscale/eda/feature_engineering.py
atscale/eda/linear_regression.py
atscale/eda/pca.py
atscale/errors/__init__.py
atscale/errors/atscale_errors.py
atscale/parsers/__init__.py
atscale/parsers/data_model_parser.py
atscale/parsers/dataset_parser.py
atscale/parsers/dictionary_parser.py
atscale/parsers/project_parser.py
atscale/project/__init__.py
atscale/project/project.py
atscale/utils/__init__.py
atscale/utils/bulk_operator_utils.py
atscale/utils/db_utils.py
atscale/utils/dimension_utils.py
atscale/utils/dmv_utils.py
atscale/utils/feature_utils.py
atscale/utils/input_utils.py
atscale/utils/metadata_utils.py
atscale/utils/model_utils.py
atscale/utils/prediction_utils.py
atscale/utils/project_utils.py
atscale/utils/query_utils.py
atscale/utils/request_utils.py
atscale/utils/time_utils.py
atscale/utils/validation_utils.py
atscale_python_api-2.4.4.dist-info/LICENSE.md
atscale_python_api-2.4.4.dist-info/METADATA
atscale_python_api-2.4.4.dist-info/WHEEL
atscale_python_api-2.4.4.dist-info/RECORD
